{
  "is_required":true,
  "types":["dict"],
  "fields":{
    "name":{
      "is_required":true,
      "types":["str"]
    },
    "schema_type":{
      "is_required":true,
      "types":["int"]
    },
    "description":{
      "is_required":false,
      "types":["str"]
    },
    "version":{
      "is_required":false,
      "types":["str"]
    },
    "company_name":{
      "is_required":false,
      "types":["str"]
    },
    "company_url":{
      "is_required":false,
      "types":["str"]
    },
    "company_logo":{
      "is_required":false,
      "types":["str"]
    },
    "license_file":{
      "is_required":false,
      "types":["str"]
    },
    "base_offset":{
      "is_required":false,
      "types":["int"]
    },
    "params":{
      "is_required":false,
      "types":["list"],
      "list_types":["dict"],
      "fields":{
        "name":{
          "is_required":true,
          "types":["str"]
        },
        "value":{
          "is_required":true,
          "types":["str","bool","int","list"],
          "list_types":["int"]
        },
        "description":{
          "is_required":false,
          "types":["str"]
        }
      }
    },
    "nodes":{
      "is_required":true,
      "types":["list"],
      "list_types":["dict"],
      "fields":{
        "fins_path":{
          "is_required":true,
          "types":["str"]
        },
        "module_name":{
          "is_required":true,
          "types":["str"]
        },
        "interface_name":{
          "is_required":false,
          "types":["str"]
        },
        "properties_offset":{
          "is_required":false,
          "types":["str","int"]
        },
        "ports_producer_name":{
          "is_required":false,
          "types":["str"]
        },
        "ports_consumer_name":{
          "is_required":false,
          "types":["str"]
        }
      }
    }
  }
}
